xicam/core/__init__.py
xicam/core/_version.py
xicam/core/data/__init__.py
xicam/core/execution/__init__.py
xicam/core/execution/camlinkexecutor.py
xicam/core/execution/daskexecutor.py
xicam/core/execution/localexecutor.py
xicam/core/execution/workflow.py
xicam/core/msg/__init__.py
xicam.core-2.1.5.dist-info/METADATA
xicam.core-2.1.5.dist-info/RECORD
xicam.core-2.1.5.dist-info/WHEEL
xicam.core-2.1.5.dist-info/top_level.txt
