Metadata-Version: 2.1
Name: xicam.core
Version: 2.1.5
Summary: The CAMERA platform for synchrotron data management, visualization, and reduction. The xicam.core package contains all backend code of the Xi-cam platform, as part of the xicam namespace package. For the gui components, see "xicam.gui".
Home-page: https://github.com/lbl-camera/Xi-cam.core
Author: Ronald J Pandolfi
Author-email: ronpandolfi@lbl.gov
License: BSD
Download-URL: https://github.com/lbl-camera/Xi-cam.core/archive/v2.0.1-alpha.tar.gz
Keywords: synchrotron analysis x-ray scattering tomography
Platform: UNKNOWN
Classifier: Development Status :: 3 - Alpha
Classifier: Intended Audience :: Science/Research
Classifier: Topic :: Scientific/Engineering :: Physics
Classifier: License :: OSI Approved :: BSD License
Classifier: Programming Language :: Python :: 3.6
Provides-Extra: tests
Requires-Dist: databroker
Requires-Dist: pathlib
Requires-Dist: distributed
Requires-Dist: dask
Provides-Extra: tests
Requires-Dist: pytest; extra == 'tests'
Requires-Dist: coverage; extra == 'tests'
